setup.py
cheap/__init__.py
cheap.egg-info/PKG-INFO
cheap.egg-info/SOURCES.txt
cheap.egg-info/dependency_links.txt
cheap.egg-info/top_level.txt