Metadata-Version: 1.1
Name: cheap
Version: 0.1
Summary: A service for locate and get the cheaper available VM
Home-page: UNKNOWN
Author: Cheaper Machine Locator.
Author-email: team@cheaper.io
License: BSD
Keywords: cloud cloud-computing cheap cheap vms hypervisor amazon
Platform: UNKNOWN
Classifier: Development Status :: 3 - Alpha
Classifier: Intended Audience :: Developers
Classifier: Operating System :: Unix 
